{
 "Start timestamp (milliseconds)": 1707787196102,
 "Current Timestamp (milliseconds)": 1707787256684,
 "Elapsed Time (nanoseconds)": 60000035480,
 "DBMS Type": "POSTGRES",
 "DBMS Version": "PostgreSQL 12.17 (Ubuntu 12.17-0ubuntu0.20.04.1) on x86_64-pc-linux-gnu, compiled by gcc (Ubuntu 9.4.0-1ubuntu1~20.04.2) 9.4.0, 64-bit",
 "Benchmark Type": "tpcc",
 "Final State": "EXIT",
 "Measured Requests": 28869,
 "isolation": "TRANSACTION_SERIALIZABLE",
 "scalefactor": "1",
 "terminals": "1",
 "Latency Distribution": {
  "95th Percentile Latency (microseconds)": 5726,
  "Maximum Latency (microseconds)": 22017,
  "Median Latency (microseconds)": 1591,
  "Minimum Latency (microseconds)": 255,
  "25th Percentile Latency (microseconds)": 743,
  "90th Percentile Latency (microseconds)": 4222,
  "99th Percentile Latency (microseconds)": 8613,
  "75th Percentile Latency (microseconds)": 2719,
  "Average Latency (microseconds)": 2071
 },
 "Throughput (requests/second)": 481.1497154801349,
 "Goodput (requests/second)": 478.68305027208964
}
