{
 "Start timestamp (milliseconds)": 1710821760048,
 "Current Timestamp (milliseconds)": 1710821820984,
 "Elapsed Time (nanoseconds)": 60000150992,
 "DBMS Type": "POSTGRES",
 "DBMS Version": "PostgreSQL 12.17 (Ubuntu 12.17-0ubuntu0.20.04.1) on x86_64-pc-linux-gnu, compiled by gcc (Ubuntu 9.4.0-1ubuntu1~20.04.2) 9.4.0, 64-bit",
 "Benchmark Type": "tpcc",
 "Final State": "EXIT",
 "Measured Requests": 21316,
 "isolation": "TRANSACTION_SERIALIZABLE",
 "scalefactor": "1",
 "terminals": "1",
 "Latency Distribution": {
  "95th Percentile Latency (microseconds)": 7776,
  "Maximum Latency (microseconds)": 54415,
  "Median Latency (microseconds)": 1913,
  "Minimum Latency (microseconds)": 269,
  "25th Percentile Latency (microseconds)": 929,
  "90th Percentile Latency (microseconds)": 6300,
  "99th Percentile Latency (microseconds)": 13883,
  "75th Percentile Latency (microseconds)": 3423,
  "Average Latency (microseconds)": 2803
 },
 "Throughput (requests/second)": 355.26577262850765,
 "Goodput (requests/second)": 353.69910990439996
}
