{
 "pg_stat_database": [
  {
   "temp_files": "0",
   "tup_returned": "761361",
   "blk_write_time": "0",
   "datname": null,
   "blks_hit": "1697629",
   "xact_commit": "0",
   "blk_read_time": "0",
   "numbackends": "0",
   "tup_fetched": "403387",
   "tup_updated": "0",
   "xact_rollback": "0",
   "tup_deleted": "0",
   "checksum_failures": null,
   "stats_reset": "2024-01-22 13:07:36.407296-08",
   "checksum_last_failure": null,
   "conflicts": "0",
   "blks_read": "66618",
   "temp_bytes": "0",
   "datid": "0",
   "deadlocks": "0",
   "tup_inserted": "5"
  },
  {
   "temp_files": "0",
   "tup_returned": "31747055",
   "blk_write_time": "0",
   "datname": "postgres",
   "blks_hit": "2549951",
   "xact_commit": "50588",
   "blk_read_time": "0",
   "numbackends": "0",
   "tup_fetched": "644458",
   "tup_updated": "0",
   "xact_rollback": "0",
   "tup_deleted": "0",
   "checksum_failures": null,
   "stats_reset": "2024-01-22 13:07:36.40726-08",
   "checksum_last_failure": null,
   "conflicts": "0",
   "blks_read": "79568",
   "temp_bytes": "0",
   "datid": "13461",
   "deadlocks": "0",
   "tup_inserted": "0"
  },
  {
   "temp_files": "0",
   "tup_returned": "27622138",
   "blk_write_time": "0",
   "datname": "benchbase_tpcc",
   "blks_hit": "2423119",
   "xact_commit": "68460",
   "blk_read_time": "0",
   "numbackends": "0",
   "tup_fetched": "689543",
   "tup_updated": "0",
   "xact_rollback": "0",
   "tup_deleted": "0",
   "checksum_failures": null,
   "stats_reset": "2024-01-28 15:04:43.021749-08",
   "checksum_last_failure": null,
   "conflicts": "0",
   "blks_read": "111050",
   "temp_bytes": "0",
   "datid": "16386",
   "deadlocks": "0",
   "tup_inserted": "0"
  },
  {
   "temp_files": "0",
   "tup_returned": "0",
   "blk_write_time": "0",
   "datname": "template1",
   "blks_hit": "0",
   "xact_commit": "0",
   "blk_read_time": "0",
   "numbackends": "0",
   "tup_fetched": "0",
   "tup_updated": "0",
   "xact_rollback": "0",
   "tup_deleted": "0",
   "checksum_failures": null,
   "stats_reset": null,
   "checksum_last_failure": null,
   "conflicts": "0",
   "blks_read": "0",
   "temp_bytes": "0",
   "datid": "1",
   "deadlocks": "0",
   "tup_inserted": "0"
  },
  {
   "temp_files": "0",
   "tup_returned": "0",
   "blk_write_time": "0",
   "datname": "template0",
   "blks_hit": "0",
   "xact_commit": "0",
   "blk_read_time": "0",
   "numbackends": "0",
   "tup_fetched": "0",
   "tup_updated": "0",
   "xact_rollback": "0",
   "tup_deleted": "0",
   "checksum_failures": null,
   "stats_reset": null,
   "checksum_last_failure": null,
   "conflicts": "0",
   "blks_read": "0",
   "temp_bytes": "0",
   "datid": "13460",
   "deadlocks": "0",
   "tup_inserted": "0"
  },
  {
   "temp_files": "0",
   "tup_returned": "58217979150",
   "blk_write_time": "0",
   "datname": "benchbase",
   "blks_hit": "54213247240",
   "xact_commit": "33464486",
   "blk_read_time": "0",
   "numbackends": "1",
   "tup_fetched": "38573339364",
   "tup_updated": "155285217",
   "xact_rollback": "63487",
   "tup_deleted": "6164076",
   "checksum_failures": null,
   "stats_reset": "2024-01-28 14:46:33.993741-08",
   "checksum_last_failure": null,
   "conflicts": "0",
   "blks_read": "220581717",
   "temp_bytes": "0",
   "datid": "16387",
   "deadlocks": "0",
   "tup_inserted": "2542441083"
  }
 ],
 "pg_stat_user_indexes": [
  {
   "indexrelname": "warehouse_pkey",
   "relname": "warehouse",
   "relid": "128856",
   "schemaname": "public",
   "idx_tup_read": "130614",
   "idx_tup_fetch": "130614",
   "idx_scan": "130614",
   "indexrelid": "128859"
  },
  {
   "indexrelname": "item_pkey",
   "relname": "item",
   "relid": "128861",
   "schemaname": "public",
   "idx_tup_read": "225633",
   "idx_tup_fetch": "225633",
   "idx_scan": "225751",
   "indexrelid": "128864"
  },
  {
   "indexrelname": "stock_pkey",
   "relname": "stock",
   "relid": "128866",
   "schemaname": "public",
   "idx_tup_read": "907149",
   "idx_tup_fetch": "899672",
   "idx_scan": "899672",
   "indexrelid": "128869"
  },
  {
   "indexrelname": "district_pkey",
   "relname": "district",
   "relid": "128881",
   "schemaname": "public",
   "idx_tup_read": "115144",
   "idx_tup_fetch": "112908",
   "idx_scan": "112908",
   "indexrelid": "128884"
  },
  {
   "indexrelname": "customer_pkey",
   "relname": "customer",
   "relid": "128891",
   "schemaname": "public",
   "idx_tup_read": "129635",
   "idx_tup_fetch": "126604",
   "idx_scan": "126604",
   "indexrelid": "128898"
  },
  {
   "indexrelname": "oorder_pkey",
   "relname": "oorder",
   "relid": "128919",
   "schemaname": "public",
   "idx_tup_read": "378470",
   "idx_tup_fetch": "378470",
   "idx_scan": "378470",
   "indexrelid": "128923"
  },
  {
   "indexrelname": "oorder_o_w_id_o_d_id_o_c_id_o_id_key",
   "relname": "oorder",
   "relid": "128919",
   "schemaname": "public",
   "idx_tup_read": "90783",
   "idx_tup_fetch": "90782",
   "idx_scan": "90782",
   "indexrelid": "128925"
  },
  {
   "indexrelname": "new_order_pkey",
   "relname": "new_order",
   "relid": "128932",
   "schemaname": "public",
   "idx_tup_read": "35790",
   "idx_tup_fetch": "21950",
   "idx_scan": "21960",
   "indexrelid": "128935"
  },
  {
   "indexrelname": "order_line_pkey",
   "relname": "order_line",
   "relid": "128942",
   "schemaname": "public",
   "idx_tup_read": "486927",
   "idx_tup_fetch": "456118",
   "idx_scan": "24229",
   "indexrelid": "128945"
  },
  {
   "indexrelname": "idx_customer_name",
   "relname": "customer",
   "relid": "128891",
   "schemaname": "public",
   "idx_tup_read": "28115",
   "idx_tup_fetch": "26679",
   "idx_scan": "7926",
   "indexrelid": "128957"
  }
 ],
 "pg_statio_user_tables": [
  {
   "idx_blks_read": null,
   "relname": "history",
   "heap_blks_hit": "127466",
   "relid": "128905",
   "schemaname": "public",
   "tidx_blks_read": null,
   "heap_blks_read": "771",
   "tidx_blks_hit": null,
   "idx_blks_hit": null,
   "toast_blks_hit": null,
   "toast_blks_read": null
  },
  {
   "idx_blks_read": "3",
   "relname": "district",
   "heap_blks_hit": "313777",
   "relid": "128881",
   "schemaname": "public",
   "tidx_blks_read": null,
   "heap_blks_read": "11",
   "tidx_blks_hit": null,
   "idx_blks_hit": "113046",
   "toast_blks_hit": null,
   "toast_blks_read": null
  },
  {
   "idx_blks_read": "445",
   "relname": "oorder",
   "heap_blks_hit": "1030850",
   "relid": "128919",
   "schemaname": "public",
   "tidx_blks_read": null,
   "heap_blks_read": "414",
   "tidx_blks_hit": null,
   "idx_blks_hit": "1817755",
   "toast_blks_hit": null,
   "toast_blks_read": null
  },
  {
   "idx_blks_read": "89",
   "relname": "new_order",
   "heap_blks_hit": "78847",
   "relid": "128932",
   "schemaname": "public",
   "tidx_blks_read": null,
   "heap_blks_read": "124",
   "tidx_blks_hit": null,
   "idx_blks_hit": "105849",
   "toast_blks_hit": null,
   "toast_blks_read": null
  },
  {
   "idx_blks_read": "278",
   "relname": "stock",
   "heap_blks_hit": "2035932",
   "relid": "128866",
   "schemaname": "public",
   "tidx_blks_read": null,
   "heap_blks_read": "5761",
   "tidx_blks_hit": null,
   "idx_blks_hit": "2016195",
   "toast_blks_hit": null,
   "toast_blks_read": null
  },
  {
   "idx_blks_read": "418",
   "relname": "customer",
   "heap_blks_hit": "366017",
   "relid": "128891",
   "schemaname": "public",
   "tidx_blks_read": "0",
   "heap_blks_read": "2532",
   "tidx_blks_hit": "0",
   "idx_blks_hit": "421478",
   "toast_blks_hit": "0",
   "toast_blks_read": "0"
  },
  {
   "idx_blks_read": "3",
   "relname": "warehouse",
   "heap_blks_hit": "292969",
   "relid": "128856",
   "schemaname": "public",
   "tidx_blks_read": null,
   "heap_blks_read": "9",
   "tidx_blks_hit": null,
   "idx_blks_hit": "130623",
   "toast_blks_hit": null,
   "toast_blks_read": null
  },
  {
   "idx_blks_read": "2346",
   "relname": "order_line",
   "heap_blks_hit": "1687013",
   "relid": "128942",
   "schemaname": "public",
   "tidx_blks_read": null,
   "heap_blks_read": "7371",
   "tidx_blks_hit": null,
   "idx_blks_hit": "902361",
   "toast_blks_hit": null,
   "toast_blks_read": null
  },
  {
   "idx_blks_read": "277",
   "relname": "item",
   "heap_blks_hit": "429558",
   "relid": "128861",
   "schemaname": "public",
   "tidx_blks_read": null,
   "heap_blks_read": "1388",
   "tidx_blks_hit": null,
   "idx_blks_hit": "651371",
   "toast_blks_hit": null,
   "toast_blks_read": null
  }
 ],
 "pg_stat_bgwriter": [{
  "checkpoint_write_time": "26045439",
  "buffers_backend_fsync": "0",
  "buffers_clean": "36340983",
  "checkpoints_req": "591",
  "checkpoint_sync_time": "193494",
  "stats_reset": "2024-01-22 13:07:25.31685-08",
  "buffers_checkpoint": "4933735",
  "checkpoints_timed": "4766",
  "buffers_alloc": "124927721",
  "buffers_backend": "175574689",
  "maxwritten_clean": "317815"
 }],
 "pg_stat_user_tables": [
  {
   "n_tup_upd": "0",
   "relname": "new_order",
   "analyze_count": "0",
   "n_tup_del": "10980",
   "relid": "128932",
   "schemaname": "public",
   "n_tup_ins": "21608",
   "last_autoanalyze": "2024-03-18 21:26:07.741358-07",
   "last_autovacuum": "2024-03-18 21:26:07.734331-07",
   "last_analyze": null,
   "n_mod_since_analyze": "3084",
   "idx_tup_fetch": "21950",
   "seq_tup_read": "0",
   "vacuum_count": "0",
   "autoanalyze_count": "2",
   "autovacuum_count": "1",
   "n_live_tup": "10517",
   "n_dead_tup": "1400",
   "last_vacuum": null,
   "n_tup_hot_upd": "0",
   "seq_scan": "1",
   "idx_scan": "21960"
  },
  {
   "n_tup_upd": "12043",
   "relname": "warehouse",
   "analyze_count": "0",
   "n_tup_del": "0",
   "relid": "128856",
   "schemaname": "public",
   "n_tup_ins": "1",
   "last_autoanalyze": "2024-03-18 21:26:05.643719-07",
   "last_autovacuum": null,
   "last_analyze": null,
   "n_mod_since_analyze": "2047",
   "idx_tup_fetch": "130614",
   "seq_tup_read": "6194",
   "vacuum_count": "0",
   "autoanalyze_count": "1",
   "autovacuum_count": "0",
   "n_live_tup": "1",
   "n_dead_tup": "65",
   "last_vacuum": null,
   "n_tup_hot_upd": "12037",
   "seq_scan": "6195",
   "idx_scan": "130614"
  },
  {
   "n_tup_upd": "0",
   "relname": "item",
   "analyze_count": "0",
   "n_tup_del": "0",
   "relid": "128861",
   "schemaname": "public",
   "n_tup_ins": "100000",
   "last_autoanalyze": "2024-03-18 21:25:06.390244-07",
   "last_autovacuum": null,
   "last_analyze": null,
   "n_mod_since_analyze": "0",
   "idx_tup_fetch": "225633",
   "seq_tup_read": "0",
   "vacuum_count": "0",
   "autoanalyze_count": "1",
   "autovacuum_count": "0",
   "n_live_tup": "100000",
   "n_dead_tup": "0",
   "last_vacuum": null,
   "n_tup_hot_upd": "0",
   "seq_scan": "1",
   "idx_scan": "225751"
  },
  {
   "n_tup_upd": "10980",
   "relname": "oorder",
   "analyze_count": "0",
   "n_tup_del": "0",
   "relid": "128919",
   "schemaname": "public",
   "n_tup_ins": "42608",
   "last_autoanalyze": "2024-03-18 21:26:07.711419-07",
   "last_autovacuum": null,
   "last_analyze": null,
   "n_mod_since_analyze": "3084",
   "idx_tup_fetch": "469252",
   "seq_tup_read": "0",
   "vacuum_count": "0",
   "autoanalyze_count": "2",
   "autovacuum_count": "0",
   "n_live_tup": "42509",
   "n_dead_tup": "2512",
   "last_vacuum": null,
   "n_tup_hot_upd": "8710",
   "seq_scan": "2",
   "idx_scan": "469252"
  },
  {
   "n_tup_upd": "124502",
   "relname": "stock",
   "analyze_count": "0",
   "n_tup_del": "0",
   "relid": "128866",
   "schemaname": "public",
   "n_tup_ins": "100000",
   "last_autoanalyze": "2024-03-18 21:26:06.672728-07",
   "last_autovacuum": null,
   "last_analyze": null,
   "n_mod_since_analyze": "19177",
   "idx_tup_fetch": "899672",
   "seq_tup_read": "0",
   "vacuum_count": "0",
   "autoanalyze_count": "2",
   "autovacuum_count": "0",
   "n_live_tup": "100004",
   "n_dead_tup": "5884",
   "last_vacuum": null,
   "n_tup_hot_upd": "118584",
   "seq_scan": "1",
   "idx_scan": "899672"
  },
  {
   "n_tup_upd": "24651",
   "relname": "district",
   "analyze_count": "0",
   "n_tup_del": "0",
   "relid": "128881",
   "schemaname": "public",
   "n_tup_ins": "10",
   "last_autoanalyze": "2024-03-18 21:26:06.687755-07",
   "last_autovacuum": "2024-03-18 21:26:06.685152-07",
   "last_analyze": null,
   "n_mod_since_analyze": "3802",
   "idx_tup_fetch": "112908",
   "seq_tup_read": "92633",
   "vacuum_count": "0",
   "autoanalyze_count": "1",
   "autovacuum_count": "1",
   "n_live_tup": "10",
   "n_dead_tup": "28",
   "last_vacuum": null,
   "n_tup_hot_upd": "24531",
   "seq_scan": "9565",
   "idx_scan": "112908"
  },
  {
   "n_tup_upd": "23023",
   "relname": "customer",
   "analyze_count": "0",
   "n_tup_del": "0",
   "relid": "128891",
   "schemaname": "public",
   "n_tup_ins": "30000",
   "last_autoanalyze": "2024-03-18 21:26:07.514329-07",
   "last_autovacuum": null,
   "last_analyze": null,
   "n_mod_since_analyze": "3265",
   "idx_tup_fetch": "153283",
   "seq_tup_read": "0",
   "vacuum_count": "0",
   "autoanalyze_count": "2",
   "autovacuum_count": "0",
   "n_live_tup": "30000",
   "n_dead_tup": "4136",
   "last_vacuum": null,
   "n_tup_hot_upd": "19791",
   "seq_scan": "2",
   "idx_scan": "134530"
  },
  {
   "n_tup_upd": "109807",
   "relname": "order_line",
   "analyze_count": "0",
   "n_tup_del": "0",
   "relid": "128942",
   "schemaname": "public",
   "n_tup_ins": "424542",
   "last_autoanalyze": "2024-03-18 21:26:08.814481-07",
   "last_autovacuum": "2024-03-18 21:26:08.48159-07",
   "last_analyze": null,
   "n_mod_since_analyze": "26946",
   "idx_tup_fetch": "456118",
   "seq_tup_read": "0",
   "vacuum_count": "0",
   "autoanalyze_count": "2",
   "autovacuum_count": "1",
   "n_live_tup": "424241",
   "n_dead_tup": "6305",
   "last_vacuum": null,
   "n_tup_hot_upd": "79239",
   "seq_scan": "1",
   "idx_scan": "24229"
  },
  {
   "n_tup_upd": "0",
   "relname": "history",
   "analyze_count": "0",
   "n_tup_del": "0",
   "relid": "128905",
   "schemaname": "public",
   "n_tup_ins": "42043",
   "last_autoanalyze": "2024-03-18 21:26:07.647516-07",
   "last_autovacuum": null,
   "last_analyze": null,
   "n_mod_since_analyze": "1664",
   "idx_tup_fetch": null,
   "seq_tup_read": "0",
   "vacuum_count": "0",
   "autoanalyze_count": "2",
   "autovacuum_count": "0",
   "n_live_tup": "42044",
   "n_dead_tup": "0",
   "last_vacuum": null,
   "n_tup_hot_upd": "0",
   "seq_scan": "0",
   "idx_scan": null
  }
 ],
 "pg_statio_user_indexes": [
  {
   "idx_blks_read": "3",
   "indexrelname": "warehouse_pkey",
   "relname": "warehouse",
   "relid": "128856",
   "schemaname": "public",
   "idx_blks_hit": "130623",
   "indexrelid": "128859"
  },
  {
   "idx_blks_read": "277",
   "indexrelname": "item_pkey",
   "relname": "item",
   "relid": "128861",
   "schemaname": "public",
   "idx_blks_hit": "651371",
   "indexrelid": "128864"
  },
  {
   "idx_blks_read": "278",
   "indexrelname": "stock_pkey",
   "relname": "stock",
   "relid": "128866",
   "schemaname": "public",
   "idx_blks_hit": "2016195",
   "indexrelid": "128869"
  },
  {
   "idx_blks_read": "3",
   "indexrelname": "district_pkey",
   "relname": "district",
   "relid": "128881",
   "schemaname": "public",
   "idx_blks_hit": "113046",
   "indexrelid": "128884"
  },
  {
   "idx_blks_read": "117",
   "indexrelname": "customer_pkey",
   "relname": "customer",
   "relid": "128891",
   "schemaname": "public",
   "idx_blks_hit": "321128",
   "indexrelid": "128898"
  },
  {
   "idx_blks_read": "218",
   "indexrelname": "oorder_pkey",
   "relname": "oorder",
   "relid": "128919",
   "schemaname": "public",
   "idx_blks_hit": "846703",
   "indexrelid": "128923"
  },
  {
   "idx_blks_read": "227",
   "indexrelname": "oorder_o_w_id_o_d_id_o_c_id_o_id_key",
   "relname": "oorder",
   "relid": "128919",
   "schemaname": "public",
   "idx_blks_hit": "971052",
   "indexrelid": "128925"
  },
  {
   "idx_blks_read": "89",
   "indexrelname": "new_order_pkey",
   "relname": "new_order",
   "relid": "128932",
   "schemaname": "public",
   "idx_blks_hit": "105849",
   "indexrelid": "128935"
  },
  {
   "idx_blks_read": "2346",
   "indexrelname": "order_line_pkey",
   "relname": "order_line",
   "relid": "128942",
   "schemaname": "public",
   "idx_blks_hit": "902361",
   "indexrelid": "128945"
  },
  {
   "idx_blks_read": "301",
   "indexrelname": "idx_customer_name",
   "relname": "customer",
   "relid": "128891",
   "schemaname": "public",
   "idx_blks_hit": "100350",
   "indexrelid": "128957"
  }
 ],
 "pg_stat_archiver": [{
  "last_failed_wal": null,
  "archived_count": "0",
  "last_archived_wal": null,
  "stats_reset": "2024-01-22 13:07:25.31685-08",
  "last_archived_time": null,
  "failed_count": "0",
  "last_failed_time": null
 }],
 "pg_stat_database_conflicts": [
  {
   "confl_tablespace": "0",
   "confl_deadlock": "0",
   "datname": "postgres",
   "confl_lock": "0",
   "datid": "13461",
   "confl_bufferpin": "0",
   "confl_snapshot": "0"
  },
  {
   "confl_tablespace": "0",
   "confl_deadlock": "0",
   "datname": "benchbase_tpcc",
   "confl_lock": "0",
   "datid": "16386",
   "confl_bufferpin": "0",
   "confl_snapshot": "0"
  },
  {
   "confl_tablespace": "0",
   "confl_deadlock": "0",
   "datname": "template1",
   "confl_lock": "0",
   "datid": "1",
   "confl_bufferpin": "0",
   "confl_snapshot": "0"
  },
  {
   "confl_tablespace": "0",
   "confl_deadlock": "0",
   "datname": "template0",
   "confl_lock": "0",
   "datid": "13460",
   "confl_bufferpin": "0",
   "confl_snapshot": "0"
  },
  {
   "confl_tablespace": "0",
   "confl_deadlock": "0",
   "datname": "benchbase",
   "confl_lock": "0",
   "datid": "16387",
   "confl_bufferpin": "0",
   "confl_snapshot": "0"
  }
 ]
}