{
 "pg_stat_database": [
  {
   "temp_files": "0",
   "tup_returned": "765657",
   "blk_write_time": "0",
   "datname": null,
   "blks_hit": "1711962",
   "xact_commit": "0",
   "blk_read_time": "0",
   "numbackends": "0",
   "tup_fetched": "406069",
   "tup_updated": "0",
   "xact_rollback": "0",
   "tup_deleted": "0",
   "checksum_failures": null,
   "stats_reset": "2024-01-22 13:07:36.407296-08",
   "checksum_last_failure": null,
   "conflicts": "0",
   "blks_read": "67885",
   "temp_bytes": "0",
   "datid": "0",
   "deadlocks": "0",
   "tup_inserted": "5"
  },
  {
   "temp_files": "0",
   "tup_returned": "31824923",
   "blk_write_time": "0",
   "datname": "postgres",
   "blks_hit": "2592455",
   "xact_commit": "50672",
   "blk_read_time": "0",
   "numbackends": "0",
   "tup_fetched": "667516",
   "tup_updated": "0",
   "xact_rollback": "0",
   "tup_deleted": "0",
   "checksum_failures": null,
   "stats_reset": "2024-01-22 13:07:36.40726-08",
   "checksum_last_failure": null,
   "conflicts": "0",
   "blks_read": "82382",
   "temp_bytes": "0",
   "datid": "13461",
   "deadlocks": "0",
   "tup_inserted": "0"
  },
  {
   "temp_files": "0",
   "tup_returned": "27705566",
   "blk_write_time": "0",
   "datname": "benchbase_tpcc",
   "blks_hit": "2466278",
   "xact_commit": "70010",
   "blk_read_time": "0",
   "numbackends": "0",
   "tup_fetched": "713207",
   "tup_updated": "0",
   "xact_rollback": "0",
   "tup_deleted": "0",
   "checksum_failures": null,
   "stats_reset": "2024-01-28 15:04:43.021749-08",
   "checksum_last_failure": null,
   "conflicts": "0",
   "blks_read": "114863",
   "temp_bytes": "0",
   "datid": "16386",
   "deadlocks": "0",
   "tup_inserted": "0"
  },
  {
   "temp_files": "0",
   "tup_returned": "0",
   "blk_write_time": "0",
   "datname": "template1",
   "blks_hit": "0",
   "xact_commit": "0",
   "blk_read_time": "0",
   "numbackends": "0",
   "tup_fetched": "0",
   "tup_updated": "0",
   "xact_rollback": "0",
   "tup_deleted": "0",
   "checksum_failures": null,
   "stats_reset": null,
   "checksum_last_failure": null,
   "conflicts": "0",
   "blks_read": "0",
   "temp_bytes": "0",
   "datid": "1",
   "deadlocks": "0",
   "tup_inserted": "0"
  },
  {
   "temp_files": "0",
   "tup_returned": "0",
   "blk_write_time": "0",
   "datname": "template0",
   "blks_hit": "0",
   "xact_commit": "0",
   "blk_read_time": "0",
   "numbackends": "0",
   "tup_fetched": "0",
   "tup_updated": "0",
   "xact_rollback": "0",
   "tup_deleted": "0",
   "checksum_failures": null,
   "stats_reset": null,
   "checksum_last_failure": null,
   "conflicts": "0",
   "blks_read": "0",
   "temp_bytes": "0",
   "datid": "13460",
   "deadlocks": "0",
   "tup_inserted": "0"
  },
  {
   "temp_files": "0",
   "tup_returned": "58315070466",
   "blk_write_time": "0",
   "datname": "benchbase",
   "blks_hit": "54684597835",
   "xact_commit": "34592068",
   "blk_read_time": "0",
   "numbackends": "1",
   "tup_fetched": "38663992181",
   "tup_updated": "165493591",
   "xact_rollback": "67644",
   "tup_deleted": "6562296",
   "checksum_failures": null,
   "stats_reset": "2024-01-28 14:46:33.993741-08",
   "checksum_last_failure": null,
   "conflicts": "0",
   "blks_read": "221504014",
   "temp_bytes": "0",
   "datid": "16387",
   "deadlocks": "0",
   "tup_inserted": "2573001624"
  }
 ],
 "pg_stat_user_indexes": [
  {
   "indexrelname": "stock_pkey",
   "relname": "stock",
   "relid": "134825",
   "schemaname": "public",
   "idx_tup_read": "726139",
   "idx_tup_fetch": "719625",
   "idx_scan": "719625",
   "indexrelid": "134828"
  },
  {
   "indexrelname": "district_pkey",
   "relname": "district",
   "relid": "134840",
   "schemaname": "public",
   "idx_tup_read": "98495",
   "idx_tup_fetch": "95506",
   "idx_scan": "95506",
   "indexrelid": "134843"
  },
  {
   "indexrelname": "warehouse_pkey",
   "relname": "warehouse",
   "relid": "134815",
   "schemaname": "public",
   "idx_tup_read": "120319",
   "idx_tup_fetch": "120319",
   "idx_scan": "120319",
   "indexrelid": "134818"
  },
  {
   "indexrelname": "item_pkey",
   "relname": "item",
   "relid": "134820",
   "schemaname": "public",
   "idx_tup_read": "186504",
   "idx_tup_fetch": "186504",
   "idx_scan": "186594",
   "indexrelid": "134823"
  },
  {
   "indexrelname": "customer_pkey",
   "relname": "customer",
   "relid": "134850",
   "schemaname": "public",
   "idx_tup_read": "109149",
   "idx_tup_fetch": "106405",
   "idx_scan": "106405",
   "indexrelid": "134857"
  },
  {
   "indexrelname": "oorder_pkey",
   "relname": "oorder",
   "relid": "134878",
   "schemaname": "public",
   "idx_tup_read": "350898",
   "idx_tup_fetch": "350898",
   "idx_scan": "350898",
   "indexrelid": "134882"
  },
  {
   "indexrelname": "oorder_o_w_id_o_d_id_o_c_id_o_id_key",
   "relname": "oorder",
   "relid": "134878",
   "schemaname": "public",
   "idx_tup_read": "69054",
   "idx_tup_fetch": "69054",
   "idx_scan": "69054",
   "indexrelid": "134884"
  },
  {
   "indexrelname": "new_order_pkey",
   "relname": "new_order",
   "relid": "134891",
   "schemaname": "public",
   "idx_tup_read": "25460",
   "idx_tup_fetch": "15843",
   "idx_scan": "15860",
   "indexrelid": "134894"
  },
  {
   "indexrelname": "order_line_pkey",
   "relname": "order_line",
   "relid": "134901",
   "schemaname": "public",
   "idx_tup_read": "350464",
   "idx_tup_fetch": "329103",
   "idx_scan": "17463",
   "indexrelid": "134904"
  },
  {
   "indexrelname": "idx_customer_name",
   "relname": "customer",
   "relid": "134850",
   "schemaname": "public",
   "idx_tup_read": "20230",
   "idx_tup_fetch": "19099",
   "idx_scan": "5429",
   "indexrelid": "134916"
  }
 ],
 "pg_statio_user_tables": [
  {
   "idx_blks_read": "3",
   "relname": "warehouse",
   "heap_blks_hit": "255971",
   "relid": "134815",
   "schemaname": "public",
   "tidx_blks_read": null,
   "heap_blks_read": "8",
   "tidx_blks_hit": null,
   "idx_blks_hit": "120329",
   "toast_blks_hit": null,
   "toast_blks_read": null
  },
  {
   "idx_blks_read": "277",
   "relname": "stock",
   "heap_blks_hit": "1699110",
   "relid": "134825",
   "schemaname": "public",
   "tidx_blks_read": null,
   "heap_blks_read": "4727",
   "tidx_blks_hit": null,
   "idx_blks_hit": "1655077",
   "toast_blks_hit": null,
   "toast_blks_read": null
  },
  {
   "idx_blks_read": "3",
   "relname": "district",
   "heap_blks_hit": "258637",
   "relid": "134840",
   "schemaname": "public",
   "tidx_blks_read": null,
   "heap_blks_read": "11",
   "tidx_blks_hit": null,
   "idx_blks_hit": "95622",
   "toast_blks_hit": null,
   "toast_blks_read": null
  },
  {
   "idx_blks_read": "415",
   "relname": "customer",
   "heap_blks_hit": "315620",
   "relid": "134850",
   "schemaname": "public",
   "tidx_blks_read": "0",
   "heap_blks_read": "2665",
   "tidx_blks_hit": "0",
   "idx_blks_hit": "371850",
   "toast_blks_hit": "0",
   "toast_blks_read": "0"
  },
  {
   "idx_blks_read": "398",
   "relname": "oorder",
   "heap_blks_hit": "922255",
   "relid": "134878",
   "schemaname": "public",
   "tidx_blks_read": null,
   "heap_blks_read": "323",
   "tidx_blks_hit": null,
   "idx_blks_hit": "1519550",
   "toast_blks_hit": null,
   "toast_blks_read": null
  },
  {
   "idx_blks_read": "276",
   "relname": "item",
   "heap_blks_hit": "390451",
   "relid": "134820",
   "schemaname": "public",
   "tidx_blks_read": null,
   "heap_blks_read": "1344",
   "tidx_blks_hit": null,
   "idx_blks_hit": "573058",
   "toast_blks_hit": null,
   "toast_blks_read": null
  },
  {
   "idx_blks_read": "76",
   "relname": "new_order",
   "heap_blks_hit": "61328",
   "relid": "134891",
   "schemaname": "public",
   "tidx_blks_read": null,
   "heap_blks_read": "92",
   "tidx_blks_hit": null,
   "idx_blks_hit": "75452",
   "toast_blks_hit": null,
   "toast_blks_read": null
  },
  {
   "idx_blks_read": "1807",
   "relname": "order_line",
   "heap_blks_hit": "1458522",
   "relid": "134901",
   "schemaname": "public",
   "tidx_blks_read": null,
   "heap_blks_read": "4908",
   "tidx_blks_hit": null,
   "idx_blks_hit": "742555",
   "toast_blks_hit": null,
   "toast_blks_read": null
  },
  {
   "idx_blks_read": null,
   "relname": "history",
   "heap_blks_hit": "116384",
   "relid": "134864",
   "schemaname": "public",
   "tidx_blks_read": null,
   "heap_blks_read": "577",
   "tidx_blks_hit": null,
   "idx_blks_hit": null,
   "toast_blks_hit": null,
   "toast_blks_read": null
  }
 ],
 "pg_stat_bgwriter": [{
  "checkpoint_write_time": "26045439",
  "buffers_backend_fsync": "0",
  "buffers_clean": "36572307",
  "checkpoints_req": "591",
  "checkpoint_sync_time": "193494",
  "stats_reset": "2024-01-22 13:07:25.31685-08",
  "buffers_checkpoint": "4933735",
  "checkpoints_timed": "4766",
  "buffers_alloc": "125764945",
  "buffers_backend": "176294057",
  "maxwritten_clean": "318183"
 }],
 "pg_stat_user_tables": [
  {
   "n_tup_upd": "85610",
   "relname": "stock",
   "analyze_count": "0",
   "n_tup_del": "0",
   "relid": "134825",
   "schemaname": "public",
   "n_tup_ins": "100000",
   "last_autoanalyze": "2024-03-18 22:32:49.060743-07",
   "last_autovacuum": null,
   "last_analyze": null,
   "n_mod_since_analyze": "15974",
   "idx_tup_fetch": "719625",
   "seq_tup_read": "0",
   "vacuum_count": "0",
   "autoanalyze_count": "2",
   "autovacuum_count": "0",
   "n_live_tup": "100008",
   "n_dead_tup": "5109",
   "last_vacuum": null,
   "n_tup_hot_upd": "80097",
   "seq_scan": "1",
   "idx_scan": "719625"
  },
  {
   "n_tup_upd": "79531",
   "relname": "order_line",
   "analyze_count": "0",
   "n_tup_del": "0",
   "relid": "134901",
   "schemaname": "public",
   "n_tup_ins": "385650",
   "last_autoanalyze": "2024-03-18 22:32:50.829623-07",
   "last_autovacuum": "2024-03-18 22:32:50.421607-07",
   "last_analyze": null,
   "n_mod_since_analyze": "25931",
   "idx_tup_fetch": "329103",
   "seq_tup_read": "0",
   "vacuum_count": "0",
   "autoanalyze_count": "2",
   "autovacuum_count": "1",
   "n_live_tup": "385290",
   "n_dead_tup": "4493",
   "last_vacuum": null,
   "n_tup_hot_upd": "58323",
   "seq_scan": "1",
   "idx_scan": "17463"
  },
  {
   "n_tup_upd": "0",
   "relname": "new_order",
   "analyze_count": "0",
   "n_tup_del": "7930",
   "relid": "134891",
   "schemaname": "public",
   "n_tup_ins": "17652",
   "last_autoanalyze": "2024-03-18 22:32:50.154362-07",
   "last_autovacuum": "2024-03-18 22:32:50.148384-07",
   "last_analyze": null,
   "n_mod_since_analyze": "2793",
   "idx_tup_fetch": "15843",
   "seq_tup_read": "0",
   "vacuum_count": "0",
   "autoanalyze_count": "2",
   "autovacuum_count": "1",
   "n_live_tup": "9637",
   "n_dead_tup": "1385",
   "last_vacuum": null,
   "n_tup_hot_upd": "0",
   "seq_scan": "1",
   "idx_scan": "15860"
  },
  {
   "n_tup_upd": "16269",
   "relname": "customer",
   "analyze_count": "0",
   "n_tup_del": "0",
   "relid": "134850",
   "schemaname": "public",
   "n_tup_ins": "30000",
   "last_autoanalyze": "2024-03-18 22:32:49.901049-07",
   "last_autovacuum": null,
   "last_analyze": null,
   "n_mod_since_analyze": "2798",
   "idx_tup_fetch": "125504",
   "seq_tup_read": "0",
   "vacuum_count": "0",
   "autoanalyze_count": "2",
   "autovacuum_count": "0",
   "n_live_tup": "30000",
   "n_dead_tup": "4104",
   "last_vacuum": null,
   "n_tup_hot_upd": "13210",
   "seq_scan": "2",
   "idx_scan": "111834"
  },
  {
   "n_tup_upd": "0",
   "relname": "item",
   "analyze_count": "0",
   "n_tup_del": "0",
   "relid": "134820",
   "schemaname": "public",
   "n_tup_ins": "100000",
   "last_autoanalyze": "2024-03-18 22:31:49.034136-07",
   "last_autovacuum": null,
   "last_analyze": null,
   "n_mod_since_analyze": "0",
   "idx_tup_fetch": "186504",
   "seq_tup_read": "0",
   "vacuum_count": "0",
   "autoanalyze_count": "1",
   "autovacuum_count": "0",
   "n_live_tup": "100000",
   "n_dead_tup": "0",
   "last_vacuum": null,
   "n_tup_hot_upd": "0",
   "seq_scan": "1",
   "idx_scan": "186594"
  },
  {
   "n_tup_upd": "16991",
   "relname": "district",
   "analyze_count": "0",
   "n_tup_del": "0",
   "relid": "134840",
   "schemaname": "public",
   "n_tup_ins": "10",
   "last_autoanalyze": "2024-03-18 22:32:49.078033-07",
   "last_autovacuum": "2024-03-18 22:32:49.075176-07",
   "last_analyze": null,
   "n_mod_since_analyze": "3088",
   "idx_tup_fetch": "95506",
   "seq_tup_read": "73724",
   "vacuum_count": "0",
   "autoanalyze_count": "1",
   "autovacuum_count": "1",
   "n_live_tup": "10",
   "n_dead_tup": "77",
   "last_vacuum": null,
   "n_tup_hot_upd": "16890",
   "seq_scan": "7629",
   "idx_scan": "95506"
  },
  {
   "n_tup_upd": "0",
   "relname": "history",
   "analyze_count": "0",
   "n_tup_del": "0",
   "relid": "134864",
   "schemaname": "public",
   "n_tup_ins": "38339",
   "last_autoanalyze": "2024-03-18 22:32:50.044055-07",
   "last_autovacuum": null,
   "last_analyze": null,
   "n_mod_since_analyze": "1398",
   "idx_tup_fetch": null,
   "seq_tup_read": "0",
   "vacuum_count": "0",
   "autoanalyze_count": "2",
   "autovacuum_count": "0",
   "n_live_tup": "38389",
   "n_dead_tup": "0",
   "last_vacuum": null,
   "n_tup_hot_upd": "0",
   "seq_scan": "0",
   "idx_scan": null
  },
  {
   "n_tup_upd": "7930",
   "relname": "oorder",
   "analyze_count": "0",
   "n_tup_del": "0",
   "relid": "134878",
   "schemaname": "public",
   "n_tup_ins": "38652",
   "last_autoanalyze": "2024-03-18 22:32:50.123637-07",
   "last_autovacuum": null,
   "last_analyze": null,
   "n_mod_since_analyze": "2793",
   "idx_tup_fetch": "419952",
   "seq_tup_read": "0",
   "vacuum_count": "0",
   "autoanalyze_count": "2",
   "autovacuum_count": "0",
   "n_live_tup": "38556",
   "n_dead_tup": "1638",
   "last_vacuum": null,
   "n_tup_hot_upd": "6431",
   "seq_scan": "2",
   "idx_scan": "419952"
  },
  {
   "n_tup_upd": "8339",
   "relname": "warehouse",
   "analyze_count": "0",
   "n_tup_del": "0",
   "relid": "134815",
   "schemaname": "public",
   "n_tup_ins": "1",
   "last_autoanalyze": "2024-03-18 22:32:47.37613-07",
   "last_autovacuum": "2024-03-18 22:32:47.370148-07",
   "last_analyze": null,
   "n_mod_since_analyze": "1705",
   "idx_tup_fetch": "120319",
   "seq_tup_read": "5097",
   "vacuum_count": "0",
   "autoanalyze_count": "1",
   "autovacuum_count": "1",
   "n_live_tup": "1",
   "n_dead_tup": "31",
   "last_vacuum": null,
   "n_tup_hot_upd": "8336",
   "seq_scan": "5098",
   "idx_scan": "120319"
  }
 ],
 "pg_statio_user_indexes": [
  {
   "idx_blks_read": "277",
   "indexrelname": "stock_pkey",
   "relname": "stock",
   "relid": "134825",
   "schemaname": "public",
   "idx_blks_hit": "1655077",
   "indexrelid": "134828"
  },
  {
   "idx_blks_read": "3",
   "indexrelname": "district_pkey",
   "relname": "district",
   "relid": "134840",
   "schemaname": "public",
   "idx_blks_hit": "95622",
   "indexrelid": "134843"
  },
  {
   "idx_blks_read": "3",
   "indexrelname": "warehouse_pkey",
   "relname": "warehouse",
   "relid": "134815",
   "schemaname": "public",
   "idx_blks_hit": "120329",
   "indexrelid": "134818"
  },
  {
   "idx_blks_read": "276",
   "indexrelname": "item_pkey",
   "relname": "item",
   "relid": "134820",
   "schemaname": "public",
   "idx_blks_hit": "573058",
   "indexrelid": "134823"
  },
  {
   "idx_blks_read": "117",
   "indexrelname": "customer_pkey",
   "relname": "customer",
   "relid": "134850",
   "schemaname": "public",
   "idx_blks_hit": "280060",
   "indexrelid": "134857"
  },
  {
   "idx_blks_read": "190",
   "indexrelname": "oorder_pkey",
   "relname": "oorder",
   "relid": "134878",
   "schemaname": "public",
   "idx_blks_hit": "782047",
   "indexrelid": "134882"
  },
  {
   "idx_blks_read": "208",
   "indexrelname": "oorder_o_w_id_o_d_id_o_c_id_o_id_key",
   "relname": "oorder",
   "relid": "134878",
   "schemaname": "public",
   "idx_blks_hit": "737503",
   "indexrelid": "134884"
  },
  {
   "idx_blks_read": "76",
   "indexrelname": "new_order_pkey",
   "relname": "new_order",
   "relid": "134891",
   "schemaname": "public",
   "idx_blks_hit": "75452",
   "indexrelid": "134894"
  },
  {
   "idx_blks_read": "1807",
   "indexrelname": "order_line_pkey",
   "relname": "order_line",
   "relid": "134901",
   "schemaname": "public",
   "idx_blks_hit": "742555",
   "indexrelid": "134904"
  },
  {
   "idx_blks_read": "298",
   "indexrelname": "idx_customer_name",
   "relname": "customer",
   "relid": "134850",
   "schemaname": "public",
   "idx_blks_hit": "91790",
   "indexrelid": "134916"
  }
 ],
 "pg_stat_archiver": [{
  "last_failed_wal": null,
  "archived_count": "0",
  "last_archived_wal": null,
  "stats_reset": "2024-01-22 13:07:25.31685-08",
  "last_archived_time": null,
  "failed_count": "0",
  "last_failed_time": null
 }],
 "pg_stat_database_conflicts": [
  {
   "confl_tablespace": "0",
   "confl_deadlock": "0",
   "datname": "postgres",
   "confl_lock": "0",
   "datid": "13461",
   "confl_bufferpin": "0",
   "confl_snapshot": "0"
  },
  {
   "confl_tablespace": "0",
   "confl_deadlock": "0",
   "datname": "benchbase_tpcc",
   "confl_lock": "0",
   "datid": "16386",
   "confl_bufferpin": "0",
   "confl_snapshot": "0"
  },
  {
   "confl_tablespace": "0",
   "confl_deadlock": "0",
   "datname": "template1",
   "confl_lock": "0",
   "datid": "1",
   "confl_bufferpin": "0",
   "confl_snapshot": "0"
  },
  {
   "confl_tablespace": "0",
   "confl_deadlock": "0",
   "datname": "template0",
   "confl_lock": "0",
   "datid": "13460",
   "confl_bufferpin": "0",
   "confl_snapshot": "0"
  },
  {
   "confl_tablespace": "0",
   "confl_deadlock": "0",
   "datname": "benchbase",
   "confl_lock": "0",
   "datid": "16387",
   "confl_bufferpin": "0",
   "confl_snapshot": "0"
  }
 ]
}